playground/__init__.py
playground/defaults.py
playground/logger.py
playground/settings.yml
playground/version.py
playground/client/__init__.py
playground/client/config.py
playground/client/deploy.py
playground/client/helpers.py
playground/client/listing.py
playground/client/shell.py
playground/client/show.py
playground/client/stop.py
playground/client/test.py
playground/main/__init__.py
playground/main/client.py
playground/main/colors.py
playground/main/decorators.py
playground/main/repository.py
playground/main/schemas.py
playground/main/settings.py
playground/main/table.py
playground/main/templates.py
playground/main/tutorial.py
playground/main/backends/__init__.py
playground/main/backends/base.py
playground/main/backends/aws/__init__.py
playground/main/backends/aws/client.py
playground/main/backends/docker/__init__.py
playground/main/backends/docker/client.py
playground/main/backends/google/__init__.py
playground/main/backends/google/client.py
playground/main/backends/podman/__init__.py
playground/main/backends/podman/client.py
playground/tests/__init__.py
playground/tests/helpers.py
playground/tests/test_backends.py
playground/tests/test_settings.py
playground/tests/test_test.py
playground/tests/test_utils.py
playground/utils/__init__.py
playground/utils/fileio.py
playground/utils/misc.py
playground/utils/terminal.py
playground_tutorials-0.0.12.dist-info/LICENSE
playground_tutorials-0.0.12.dist-info/METADATA
playground_tutorials-0.0.12.dist-info/NOTICE
playground_tutorials-0.0.12.dist-info/WHEEL
playground_tutorials-0.0.12.dist-info/entry_points.txt
playground_tutorials-0.0.12.dist-info/top_level.txt
playground_tutorials-0.0.12.dist-info/RECORD
