Metadata-Version: 2.1
Name: playground-tutorials
Version: 0.0.12
Summary: the fun cloud wrapper 🍬️ to deploy tutorial containers! 📦️
Home-page: https://github.com/converged-computing/playground
Author: Vanessa Sochat
Author-email: vsoch@users.noreply.github.com
Maintainer: Vanessa Sochat
License: LICENSE
Keywords: cloud,tutorial,containers
Classifier: Intended Audience :: Science/Research
Classifier: Intended Audience :: Developers
Classifier: License :: OSI Approved :: MIT License
Classifier: Programming Language :: Python
Classifier: Topic :: Software Development
Classifier: Topic :: Scientific/Engineering
Classifier: Operating System :: Unix
Classifier: Programming Language :: Python :: 3.8
License-File: LICENSE
License-File: NOTICE
Requires-Dist: requests
Requires-Dist: ruamel.yaml
Requires-Dist: jsonschema
Requires-Dist: rich
Requires-Dist: cloud-select-tool
Provides-Extra: all
Requires-Dist: requests ; extra == 'all'
Requires-Dist: ruamel.yaml ; extra == 'all'
Requires-Dist: jsonschema ; extra == 'all'
Requires-Dist: rich ; extra == 'all'
Requires-Dist: cloud-select-tool ; extra == 'all'
Requires-Dist: google-auth ; extra == 'all'
Requires-Dist: google-api-python-client ; extra == 'all'
Requires-Dist: boto3 ; extra == 'all'
Requires-Dist: pytest (>=4.6.2) ; extra == 'all'
Requires-Dist: docker ; extra == 'all'
Provides-Extra: aws
Requires-Dist: boto3 ; extra == 'aws'
Provides-Extra: docker
Requires-Dist: docker ; extra == 'docker'
Provides-Extra: google
Requires-Dist: google-auth ; extra == 'google'
Requires-Dist: google-api-python-client ; extra == 'google'
